Workbook

Sheet KOL SocMed 
F3: KIM
A11: Date | B11: : 03 Nov 2025 - Rev 18 | E11: Project | F11: : Ingram Micro Innovation Day 2025
A12: Attn | B12: : Abigail Laurencia | E12: Date | F12: : 09 Dec 2025 (Tues)
A13: Client | B13: : PT Ingram Micro Indonesia | E13: Venue | F13: : Shangri-La Hotel, Jakarta
A14: Address | B14: : Jl. Ir. H. Juanda IV No 3B-C | E14: No. Order | F14: : QTN/KIM/2025/VIII/00015 B
B15: Wisma Nugra Santana Lt. 9 Suite 909
B16: Jakarta Pusat 10250
E18: KIM
A19: NO | B19: DESCRIPTION | C19: QTY | D19: Freq | E19: Price-unit | F19: Sub Total
A21: A | B21: Ingram Micro Innovation Day 2025
B22: Digital Creator & Soc Med Package
A24: 1 | B24: Design : Social Media Content , masih tunggu list timeline dari Cia | C24: 1 | D24: 1 | E24: 0 | F24: 0
B25: Video Teaser - done
B26: Quote Dewi
A29: 2 | B29: Content Creators
B30: Anjas Maradita - Tech Reviewer - SOW sbb | C30: 1 | D30: 1 | E30: 30000000 | F30: =C30*D30*E30 -> 30000000
B31: - Visit Event & Attend Podcast pas Coffe Break dan Lunch Time
B32: - Live Streaming Podcast di Youtube
B33: - IG Story 1x (post ig reels) (after Event)
B34: - 1x IG Reels (after Event, keseruan Acara)
B35: KOL Coordination (KOL Brief, Coordination, On Event Supervision) | C35: 1 | D35: 1 | E35: 1000000 | F35: =C35*D35*E35 -> 1000000
B36: Yoan Full Day
F38: =SUM(F20:F37) -> 31000000
B39: Sub Total | F39: =+F38 -> 31000000
A48: Note (Contract, Term & Condition) :
A49: 1 | B49: The Price Included PPn 11 %
A50: 2 | B50: Approval needed latest one month before in related to 3rd party
A51: 3 | B51: Cancellation fee 25 % from total amount of the project if the contract has been signed
A52: 4 | B52: Term of payment :
B53: 100 % payment after project finish
B54: Payment Transfer to : PT Kemenangan Indah Makmur
B55: Bank BCA Branch : Pondok Indah
B56: account IDR : 731.065.558.3
B57: account USD : 731.096.766.6
B58: NPWP : 02.098.562.8-013.000
B61: Prepared by : | F61: Approved by,
B68: Fanny Suwarni | F68: Abigail Laurencia
B69: KIM Marketing Services | F69: PT Ingram Micro Indonesia

Sheet PR Package BEM
F3: KIM
A11: Date | B11: : 03 Nov 2025 - Rev 18 | E11: Project | F11: : Ingram Micro Innovation Day 2025
A12: Attn | B12: : Abigail Laurencia | E12: Date | F12: : 09 Dec 2025 (Tues)
A13: Client | B13: : PT Ingram Micro Indonesia | E13: Venue | F13: : Shangri-La Hotel, Jakarta
A14: Address | B14: : Jl. Ir. H. Juanda IV No 3B-C | E14: No. Order | F14: : QTN/KIM/2025/VIII/00015 C
B15: Wisma Nugra Santana Lt. 9 Suite 909
B16: Jakarta Pusat 10250
A21: NO | B21: DESCRIPTION | C21: PIC | D21: QTY | E21: Freq | F21: Price-unit | G21: Sub Total | I21: MBTH - JGN HPS
A23: A | B23: C-Level & PR Event
A24: 1 | B24: D Day: Media Press Conference | C24: KIM | D24: 1 | E24: 1 | F24: 45000000 | G24: =D24*E24*F24 -> 45000000
B25: Media Invite (40 media)
B26: Follow up media relations activity
B27: Briefing Document for Speakers
I28: Media - Untuk media writing competition kita drop krna budget tidak masuk - 13/11
A30: 2 | B30: Post Event :Press Release (Service from Udari/KIM to IM) | C30: KIM | D30: 1 | E30: 1
B31: Press Release (Development - bilingual, and Distribution)
B32: Post Event Monitoring & Report
A34: B | B34: Production on the Day
B35: C-Level & Media Event
A37: 1 | B37: PREPARATION
B38: Supervision Hotel from preparation ( h-1 ) - Loading Unloading | C38: KIM | D38: 1 | E38: 1 | G38: =D38*E38*F38 -> 0
A40: 2 | B40: SHOW MANAGEMENT for Full Day event: C-Level & PR) | C40: KIM | D40: 1 | E40: 1 | G40: =D40*E40*F40 -> 0
B41: Project Officer | C41: KIM | D41: 1 | E41: 1
B42: Show Management: Stage Manager, Crew MC, Stage Crew, VJ | C42: KIM | D42: 1 | E42: 2
B43: Eartac | C43: KIM | D43: 1 | E43: 1
B44: Registration | C44: KIM | D44: 2 | E44: 1
A46: 3 | B46: TALENT & Documentation : Half Day
B47: Photografer | C47: KIM | D47: 1 | E47: 1 | G47: =D47*E47*F47 -> 0
B48: Video For Documentation | C48: KIM | D48: 1 | E48: 1 | G48: =D48*E48*F48 -> 0
B49: MC Media: BEM | C49: KIM | D49: 1 | E49: 1 | G49: =D49*E49*F49 -> 0
A51: 4 | B51: Creative Package
B52: 2D Design (All Material Video Bumper) | C52: KIM | D52: 1 | E52: 1 | G52: =+D52*E52*F52 -> 0
A54: 5 | B54: Production
B55: Foyer Area:
B56: Signage Digital | C56: Hotel | D56: 1 | E56: 1 | G56: =+D56*E56*F56 -> 0
B58: Electrical & Audio Visual
B59: LED P2.6 size 2,5 x4m , with Base LED | C59: KIM | D59: 1 | E59: 1.5 | G59: =+D59*E59*F59 -> 0
B60: Clicker | C60: KIM | D60: 1 | E60: 1
B61: Soundsystem 1500 watt | C61: KIM | D61: 1 | E61: 1.5 | G61: =+D61*E61*F61 -> 0
B62: TV Matador | C62: KIM | D62: 1 | E62: 1.5 | G62: =D62*E62*F62 -> 0
A64: 6 | B64: Other Cost
B65: Name Desk for C-Level | C65: KIM | D65: 30 | E65: 1 | G65: =D65*E65*F65 -> 0
B66: Lanyard + Name Badge for C-Level | C66: KIM | D66: 30 | E66: 1 | G66: =D66*E66*F66 -> 0
B67: Lanyard + Name Badge for Media | C67: KIM | D67: 50 | E67: 1 | G67: =D67*E67*F67 -> 0
B68: Room/ Night Include Breakfast | C68: KIM | D68: 1 | E68: 1 | G68: =D68*E68*F68 -> 0 | I68: 2420000 | J68: ADD ROOM SHANGRILA | K68: PT. SWADHARMA | L68: 45968
B69: Tiket PP - Citilink | C69: KIM | D69: 1 | E69: 2 | G69: =D69*E69*F69 -> 0
B72: Souvenir
B73: C-Level: Jabra | C73: IM | D73: 25 | E73: 1
B74: Media : Kipas Gojodog include logo IM , white color | C74: KIM | D74: 15 | E74: 1 | G74: =D74*E74*F74 -> 0 | I74: 150000 | J74: BRANDING KIPAS 15 | K74: TRIYANTO | L74: 45968
I75: 2416500 | J75: GOJODOG KIPAS 15 | K75: SHOPPEE | L75: 45968
B76: Belkin - 30 unit | C76: IM
G78: =SUM(G22:G77) -> 45000000
B79: Sub Total | G79: =+G78 -> 45000000
A88: Note (Contract, Term & Condition) :
A89: 1 | B89: The Price Included PPn 11 %
A90: 2 | B90: Approval needed latest one month before in related to 3rd party
A91: 3 | B91: Cancellation fee 25 % from total amount of the project if the contract has been signed
A92: 4 | B92: Term of payment :
B93: 100 % payment after project finish
B94: Payment Transfer to : PT Kemenangan Indah Makmur
B95: Bank BCA Branch : Pondok Indah
B96: account IDR : 731.065.558.3
B97: account USD : 731.096.766.6
B98: NPWP : 02.098.562.8-013.000
B101: Prepared by : | F101: Approved by,
B108: Fanny Suwarni | F108: Abigail Laurencia
B109: KIM Marketing Services | F109: PT Ingram Micro Indonesia

Sheet Registration
G4: KIM
A12: Date | B12: : 03 Nov 2025 - Rev 18 | E12: Project | F12: : Ingram Micro Innovation Day 2025
A13: Attn | B13: : Abigail Laurencia | E13: Date | F13: : 09 Dec 2025 (Tues)
A14: Client | B14: : PT Ingram Micro Indonesia | E14: Venue | F14: : Shangri-La Hotel, Jakarta
A15: Address | B15: : Jl. Ir. H. Juanda IV No 3B-C | E15: No. Order | F15: : QTN/KIM/2025/VIII/00015 D
B16: Wisma Nugra Santana Lt. 9 Suite 909
B17: Jakarta Pusat 10250
A22: NO | B22: DESCRIPTION | C22: PIC | D22: QTY | E22: Freq | F22: Price-unit | G22: Sub Total
A23: 1 | B23: Microsite Customer & Partner - additional request for Content | C23: Michael | D23: 1 | E23: 1 | F23: 5000000 | G23: =D23*E23*F23 -> 5000000
B24: Registration, Self Checkin, System Booth Tour, Feedback form
A26: 2 | B26: Registration System | C26: Michael | D26: 1 | E26: 1 | F26: 3000000 | G26: =D26*E26*F26 -> 3000000 | I26: VIA WA CALL… KATANYA DIA ACC ITU 7,5 JUTA KENAPA SKRG 10JUTA? JD BALIKIN KE 7,5JUTA
B27: Registration equipment : Printer, Laptop include technician | C27: KIM | D27: 5 | E27: 1 | G27: =D27*E27*F27 -> 0 | I27: GW DAH CARI KE NO REV 17.. TULISANNYA TETEP 10JT… APA ADA BUKTI DIA ACC DI 7,5JUTA KAH?
B28: Leader registration | C28: KIM | D28: 1 | E28: 1 | G28: =D28*E28*F28 -> 0
B29: Usher Checkin | C29: KIM | D29: 2 | E29: 1 | G29: =D29*E29*F29 -> 0
B30: Usher Walkin | C30: KIM | D30: 2 | E30: 1 | G30: =D30*E30*F30 -> 0
B33: Sub Total | G33: =SUM(G23:G32) -> 8000000
A41: 2 | B41: Approval needed latest one month before in related to 3rd party
A42: 3 | B42: Cancellation fee 25 % from total amount of the project if the contract has been signed
A43: 4 | B43: Term of payment :
B44: 100 % payment after project finish
B45: Payment Transfer to : PT Kemenangan Indah Makmur
B46: Bank BCA Branch : Pondok Indah
B47: account IDR : 731.065.558.3
B48: account USD : 731.096.766.6
B49: NPWP : 02.098.562.8-013.000
B53: Prepared by : | G53: Approved by,
B60: Fanny Suwarni | G60: Abigail Laurencia
B61: KIM Marketing Services | G61: PT Ingram Micro Indonesia

Sheet Customer Event
G5: KIM
A13: Date | B13: : 03 Nov 2025 - Rev 18 | E13: Project | F13: : Ingram Micro Innovation Day 2025
A14: Attn | B14: : Abigail Laurencia | E14: Date | F14: : 09 Dec 2025 (Tues)
A15: Client | B15: : PT Ingram Micro Indonesia | E15: Venue | F15: : Shangri-La Hotel, Jakarta
A16: Address | B16: : Jl. Ir. H. Juanda IV No 3B-C | E16: No. Order | F16: : QTN/KIM/2025/VIII/00015 E
B17: Wisma Nugra Santana Lt. 9 Suite 909
B18: Jakarta Pusat 10250
F21: KIM
A22: NO | B22: DESCRIPTION | C22: PIC | D22: QTY | E22: Freq | F22: Price-unit | G22: Sub Total | I22: MBTH - JGN HPS
A24: A | B24: Ingram Micro Innovation Day 2025
B25: Customers Event
A27: 0 | B27: Venue : F& B Package
B28: Half Day Meeting Package
B29: Full Day Meeting Package
B30: Gala Dinner
B31: Free flow drink: Juice, Soft drink, Beer, Wine
A33: 1 | B33: PREPARATION
B34: Loading Unloading Team | C34: KIM | D34: 1 | E34: 1 | G34: =D34*E34*F34 -> 0
A36: 2 | B36: SHOW MANAGEMENT for Customer event + GR
B37: Project Officer | C37: KIM | D37: 1 | E37: 1 | G37: =D37*E37*F37 -> 0
B38: Customer Conference Session : Show Management: Stage Manager, Crew MC, Stage Crew, VJ, | C38: KIM | D38: 1 | E38: 1.5 | G38: =D38*E38*F38 -> 0
B39: LO Speaker - Long Shift dari C-Level - Partner Event | C39: KIM | D39: 1 | E39: 1 | G39: =D39*E39*F39 -> 0
B40: Asst LO Speaker - Sponsor | C40: KIM | D40: 1 | E40: 1 | G40: =D40*E40*F40 -> 0
B41: Eartac | C41: KIM | D41: 12 | E41: 1 | G41: =D41*E41*F41 -> 0
B42: HT | C42: KIM | D42: 15 | E42: 1 | G42: =D42*E42*F42 -> 0
B43: Perfect Que | C43: KIM | D43: 1 | E43: 1 | G43: =D43*E43*F43 -> 0
B44: Meals | C44: KIM | D44: 15 | E44: 1 | G44: =D44*E44*F44 -> 0
A46: 3 | B46: Documentation & Talent : 08.00 - 21.00
B47: Photografer | C47: FILBERT | D47: 1 | E47: 1 | G47: =D47*E47*F47 -> 0
B48: Video For Documentation | D48: 1 | E48: 1 | G48: =D48*E48*F48 -> 0
B49: Operator Livestream , Live Cam + 3 Camera = total 5 pax | C49: TMN koko | D49: 1 | E49: 1 | F49: 4500000 | G49: =D49*E49*F49 -> 4500000 | I49: =4500000+91836 -> 4591836 | J49: PAKET ALAT LIVESTREAMIN | K49: MALVIB | L49: 45968 | M49: ada filbert juga
B51: TALENT
B52: MC - Customer + Partner Dinner : Tya Ayustia | C52: KIM | D52: 1 | E52: 1 | F52: =I52 -> 15384615 | G52: =D52*E52*F52 -> 15384615 | I52: =15000000+384615 -> 15384615 | J52: MC | K52: YUSTIANI | L52: 45968
B53: MC - Gala Dinner : Rio Simamora | C53: KIM | D53: 1 | E53: 1 | G53: =D53*E53*F53 -> 0
B54: MC - Clevel, HD : Jessica William | C54: KIM | D54: 1 | E54: 1 | F54: 7500000 | G54: =D54*E54*F54 -> 7500000
B55: MC - Podcast, FD - Marcellona Siregar | C55: KIM | D55: 1 | E55: 1 | F55: =I55 -> 7692307 | G55: =D55*E55*F55 -> 7692307 | I55: =7500000+192307 -> 7692307 | J55: MC | K55: AZZARA | L55: 45968
B57: Keynote Indrawan Nugroho - 2x event : C-Level & Customer | C57: KIM | D57: 1 | E57: 1 | F57: 72500000 | G57: =D57*E57*F57 -> 72500000 | I57: =66000000+1346938 -> 67346938 | J57: SPEAKER | K57: PT. CIPTA KONSULTAN | L57: 45968
B59: Moderator Fireside Chat: Wisnu Nugroho Infokom | C59: KIM | D59: 1 | E59: 1 | F59: 4500000 | G59: =D59*E59*F59 -> 4500000
B60: Panelist:Joseph Lembayung | C60: KIM | D60: 1 | E60: 1 | F60: 5000000 | G60: =D60*E60*F60 -> 5000000
B62: Ushers - Black costume KIM | long Shift | C62: KIM | D62: 6 | E62: 1 | G62: =D62*E62*F62 -> 0
B63: SPB Security - Black Jacket costume from their own | Long Shift | C63: KIM | D63: 4 | E63: 1 | G63: =D63*E63*F63 -> 0
A65: 4 | B65: Opening Act
B66: Video Opening Revision from Star Series | C66: Dimitri | D66: 1 | E66: 1 | F66: 2500000 | G66: =D66*E66*F66 -> 2500000 | L66: revisi harga | M66: =6500000-5250000 -> 1250000
B67: Laser Show (RGB 20 Watt *Prices exc. content) - Package 2 Times | C67: FALAH | D67: 1 | E67: 1 | F67: 31000000 | G67: =D67*E67*F67 -> 31000000 | H67: cek IRMAN
B68: Content Laser | D68: 1 | E68: 1 | G68: =D68*E68*F68 -> 0
A70: 5 | B70: Creative
B71: 2D & 3D Design (All Material Video Bumper, Awarding, Flazz, Booth) | C71: KIM | D71: 1 | E71: 1 | G71: =D71*E71*F71 -> 0
A73: 6 | B73: Electrical & Audio Visual
B74: MAIN BALLROOM | C74: KIM
B75: LED P2.6 Center :size 3,5x7m , with Base LED | D75: 1 | E75: 1.5 | G75: =D75*E75*F75 -> 0
B76: Wing Left & Right LED P2.6 :size 3x5m , with Base LED | D76: 2 | E76: 1.5 | G76: =D76*E76*F76 -> 0
B77: LED Header size : 2m x50cm | D77: 1 | E77: 1 | G77: =D77*E77*F77 -> 0
B78: Railing & Additional Stage 10x3m
B79: Rigging safety LED, Gun Smoke
B81: Production Stage
B82: Flooring Stage : 19.20 x 3,6m, carpet , stairs melaminto + tangga lighted (16 modul stage dari Hotel) | C82: KIM | D82: 1 | E82: 1 | G82: =+D82*E82*F82 -> 0
B83: Wing Backdrop Ki & Ka: 4,8 x 3,5m (2 set) multiplex Finsihing flexy Korcin
B84: Electrical Installment for booth | C84: KIM | D84: 1 | E84: 1
B85: Soundsystem 10.000 watt include amplifier band (peralatan dari band bawa: keyboard, gitar, drum electric, bas ) | D85: 1 | E85: 1.5 | G85: =D85*E85*F85 -> 0
B86: Lighting: Parled 8, Fresnel 4,,moving beam 4 include rigging | D86: 1 | E86: 1.5 | G86: =D86*E86*F86 -> 0
B87: Lighting Rigging | D87: 1 | E87: 1 | G87: =D87*E87*F87 -> 0
B88: Genset 100KVA Conference ( ALL LED ) | D88: 1 | E88: 1.5 | G88: =D88*E88*F88 -> 0
B89: Genset 60KVA Conference ( Sound + Laser + electrical device Booth ) | D89: 2 | E89: 1.5 | G89: =D89*E89*F89 -> 0
B90: TV Matador | D90: 2 | E90: 1.5 | G90: =D90*E90*F90 -> 0
B91: 5 Sofa Putih & 1 Meja | D91: 1 | E91: 1 | G91: =D91*E91*F91 -> 0
A93: 7 | B93: Main Backdrop Production
B94: Wing Backdrop 2 unit ,Left Right - size : 3,5 x 4,8 m | C94: KIM | D94: 2 | E94: 1 | G94: =D94*E94*F94 -> 0
B95: Black Curtain+ Depan 40 m2 | C95: KIM | D95: 1 | E95: 1 | G95: =D95*E95*F95 -> 0
A97: 8 | B97: Other Cost
B98: Communication & Reporting | C98: KIM | D98: 1 | E98: 1 | G98: =D98*E98*F98 -> 0
B99: Lanyard + Name Badge: Customer 300 | C99: KIM | D99: 300 | E99: 1 | G99: =D99*E99*F99 -> 0
B100: Lanyard + Name Badge: IM Team | C100: KIM | D100: =50+25 -> 75 | E100: 1 | G100: =D100*E100*F100 -> 0 | K100: Cust event - Untuk name tag IM siapkan 75 pcs 13/11
B101: Concept | C101: KIM | D101: 1 | E101: 1 | G101: =D101*E101*F101 -> 0 | K101: Cust event - Laken bag juga di drop krna budget tidak masuk - 13/11
B102: Pluxee | C102: IM
B104: MUA - Ibu Dewi | C104: KIM | D104: 1 | E104: 1 | F104: 500000 | G104: =D104*E104*F104 -> 500000
G106: =SUM(G23:G105) -> 151076922
B107: Sub Total | G107: =+G106 -> 151076922
A113: Note (Contract, Term & Condition) :
A114: 1 | B114: The Price Included PPn 11 %
A115: 2 | B115: Approval needed latest one month before in related to 3rd party
A116: 3 | B116: Cancellation fee 25 % from total amount of the project if the contract has been signed
A117: 4 | B117: Term of payment :
B118: 100 % payment after project finish
B119: Payment Transfer to : PT Kemenangan Indah Makmur
B120: Bank BCA Branch : Pondok Indah
B121: account IDR : 731.065.558.3
B122: account USD : 731.096.766.6
B123: NPWP : 02.098.562.8-013.000
B126: Prepared by : | G126: Approved by,
B133: Fanny Suwarni | G133: Abigail Laurencia
B134: KIM Marketing Services | G134: PT Ingram Micro Indonesia

Sheet Partner Event
G6: KIM
A14: Date | B14: : 03 Nov 2025 - Rev 18 | F14: Project | G14: : Ingram Micro Innovation Day 2025
A15: Attn | B15: : Abigail Laurencia | F15: Date | G15: : 09 Dec 2025 (Tues)
A16: Client | B16: : PT Ingram Micro Indonesia | F16: Venue | G16: : Shangri-La Hotel, Jakarta
A17: Address | B17: : Jl. Ir. H. Juanda IV No 3B-C | F17: No. Order | G17: : QTN/KIM/2025/VIII/00015 F
B18: Wisma Nugra Santana Lt. 9 Suite 909
B19: Jakarta Pusat 10250
F22: KIM
A23: NO | B23: DESCRIPTION | C23: PIC | D23: QTY | E23: Freq | F23: Price-unit | G23: Sub Total | K23: MBTH - JGN HPS
A25: A | B25: Ingram Micro Innovation Day 2025
B26: Partner Gathering
A28: 2 | B28: SHOW MANAGEMENT for Partner event + GR
B29: Partner Session : Show Management: Stage Manager, Crew MC, Stage Crew, VJ, | C29: KIM | D29: 1 | E29: 1 | G29: =D29*E29*F29 -> 0
B30: Talent Coord | C30: KIM | D30: 1 | E30: 1 | G30: =D30*E30*F30 -> 0
B31: Meals | C31: KIM | D31: 15 | E31: 1 | G31: =D31*E31*F31 -> 0
A33: 3 | B33: TALENT
B34: Entertainment : Latte Matte - 120 mnt | C34: KIM | D34: 1 | E34: 1 | G34: =D34*E34*F34 -> 0
B35: Riders : Meals + drinks , Make Up Room | C35: KIM | D35: 1 | E35: 1 | G35: =D35*E35*F35 -> 0
B36: Alt : TBC
A38: 5 | B38: Creative
B39: Video Awarding 2D & sdikit 3D - 10 award | C39: Falah | D39: 1 | E39: 1 | F39: 9000000 | G39: =D39*E39*F39 -> 9000000
A41: 6 | B41: Award Thropy
B42: Plaque | C42: KIM | D42: 10 | E42: 1 | F42: 850000 | G42: =D42*E42*F42 -> 8500000 | K42: 8500000 | L42: PLAKAT 10 | M42: YOKI | N42: 45968
A44: 7 | B44: Other Cost
B45: Lanyard + Name Badge : Partner 350 | C45: KIM | D45: 350 | E45: 1 | G45: =D45*E45*F45 -> 0 | K45: 682564 | L45: NAME BADGE - 850 | M45: SHOPPEE | N45: 45968
B46: Concept | C46: KIM | D46: 1 | E46: 1 | G46: =D46*E46*F46 -> 0
B47: Photo Glambot - 6 hours only @ Partner Event | C47: KIM | D47: 1 | E47: 1 | G47: =D47*E47*F47 -> 0 | K47: =8500000+173469 -> 8673469 | L47: GLAMBOTH | M47: PT. VARBEL | N47: 45968
G48: =D48*E48*F48 -> 0
B49: Costume for Leader - Ika, bu Mira, Hotland, JT, Hendrik, Justin, Rio | C49: KIM | D49: =11+6-10 -> 7 | E49: 1 | G49: =D49*E49*F49 -> 0 | K49: =22500000+459184 -> 22959184 | L49: SEWA COSTUM LEADER N BU DEWI | M49: GALIH | N49: 45974 | P49: Men 11 , Female 6 | S49: update meeting 12/11 + 3
B50: Costume for bu Dewi | C50: KIM | D50: 1 | E50: 1 | F50: 2500000 | G50: =D50*E50*F50 -> 2500000
B51: MUA for Men | C51: KIM | D51: =11-6 -> 5 | E51: 1 | F51: 300000 | G51: =D51*E51*F51 -> 1500000 | K51: gw kaga ngarti mksdnya apa | M51: Partner - Untuk baju leader & make up sesuaikan hanya untuk bu dewi, ika, bu mira, hotland, JT, Hendrik, justin, rio - 13/11
B52: MUA for Female | C52: KIM | D52: =6-4 -> 2 | E52: 1 | F52: 500000 | G52: =D52*E52*F52 -> 1000000
B54: Meja LED for Laptop Prizes - Xvantage member | C54: KIM | D54: 3 | E54: 1 | G54: =D54*E54*F54 -> 0
B55: Signage | C55: KIM | D55: 1 | E55: 1 | G55: =D55*E55*F55 -> 0 | K55: dr roll up jadi signage | M55: 1500000 kayu dpt 2 pcs, tripod banner 3 @125rb
B56: - Signage Area | C56: KIM | D56: 2 | E56: 1
B57: - Tripod banner (laptop) | C57: KIM | D57: 3 | E57: 1
B59: Custome - Astronaut | C59: KIM | D59: 1 | E59: 1 | G59: =D59*E59*F59 -> 0 | K59: beli baju usher 9 org x 500rb
B60: Crew - utk laptop | C60: KIM | D60: 3 | E60: 1 | G60: =D60*E60*F60 -> 0 | M60: Partner - Usher astronut di hilangkan - 13/11
B61: Ipad | C61: KIM | D61: =3-1 -> 2 | E61: 1 | G61: =D61*E61*F61 -> 0 | M61: Partner - Ipad hanya 2 aja - 13/11
A63: 8 | B63: Additional:
B64: Wayang Plaque | C64: KIM | D64: 2 | E64: 1 | G64: =D64*E64*F64 -> 0 | N64: Lunch dinner bu dewi - drop (online aja) - 13/11
N65: Lunch box pr - drop- 13/11
G66: =SUM(G24:G65) -> 22500000 | K66: =+#REF!+#REF!+K65 -> #REF! | N66: C CIA KG MO BAYAR KRN CMN NAMBAH KOLOM AJE - Additional colom registrasi - drop VIA CALL 13/11
B67: Sub Total | G67: =+G66 -> 22500000
A73: Note (Contract, Term & Condition) :
A74: 1 | B74: The Price Included PPn 11 %
A75: 2 | B75: Approval needed latest one month before in related to 3rd party
A76: 3 | B76: Cancellation fee 25 % from total amount of the project if the contract has been signed
A77: 4 | B77: Term of payment :
B78: 100 % payment after project finish
B79: Payment Transfer to : PT Kemenangan Indah Makmur
B80: Bank BCA Branch : Pondok Indah
B81: account IDR : 731.065.558.3
B82: account USD : 731.096.766.6
B83: NPWP : 02.098.562.8-013.000
B85: Prepared by : | G85: Approved by,
B92: Fanny Suwarni | G92: Abigail Laurencia
B93: KIM Marketing Services | G93: PT Ingram Micro Indonesia

Sheet Booth
A9: Date | B9: : 03 Nov 2025 - Rev 18 | F9: Project | G9: : Ingram Micro Innovation Day 2025
A10: Attn | B10: : Abigail Laurencia | F10: Date | G10: : 09 Dec 2025 (Tues)
A11: Client | B11: : PT Ingram Micro Indonesia | F11: Venue | G11: : Shangri-La Hotel, Jakarta
A12: Address | B12: : Jl. Ir. H. Juanda IV No 3B-C | F12: No. Order | G12: : QTN/KIM/2025/VIII/00015 A
B13: Wisma Nugra Santana Lt. 9 Suite 909
B14: Jakarta Pusat 10250
A16: NO | B16: DESCRIPTION | C16: PIC | D16: PIC | E16: QTY | F16: Freq | G16: Price-unit | H16: Sub Total
A18: A | B18: BOOTH PRODUCTION
A20: 1 | B20: D Day-EVENT : include preparation | D20: KIM
B21: Production & Booth team | C21: KIM | E21: 4 | F21: 1 | H21: =E21*F21*G21 -> 0
B22: PIC Foyer | C22: KIM | E22: 2 | F22: 1 | H22: =E22*F22*G22 -> 0
B23: PIC Booth | C23: KIM | E23: 2 | F23: 1 | H23: =E23*F23*G23 -> 0
B24: PIC Activity | E24: 1 | F24: 1 | H24: =E24*F24*G24 -> 0
B25: Logistic | C25: KIM | E25: 2 | F25: 2 | H25: =E25*F25*G25 -> 0
B26: Runner | C26: KIM | E26: 5 | F26: 1 | H26: =E26*F26*G26 -> 0
B27: HT | C27: KIM | E27: =E21+E22+E23+E25+E26 -> 15 | F27: 1 | H27: =E27*F27*G27 -> 0
B28: Meals - long shift | C28: KIM | E28: =E27 -> 15 | F28: 1 | H28: =E28*F28*G28 -> 0
A30: 3 | B30: Production
B32: Foyer Area:
B33: GATE (tinggi 3,6mx 3m-H) diameter 2,4m Lighted LED Flex , 2 D Pop up | D33: KIM | E33: 1 | F33: 1 | H33: =+E33*F33*G33 -> 0 | J33: 1. Booth - harga gate di kurangin dikit deh =( - 13/11
B34: Logo Lighted cutting sticker & LED Strip
B36: REGISTRATION AREA | D36: KIM | E36: 1 | F36: 1 | H36: =+E36*F36*G36 -> 0
B37: Backdrop Registration size L, size A: 4,8 x 2,44m size B ; 2,44 x 2,44m | E37: 1 | F37: 1 | H37: =+E37*F37*G37 -> 0
B38: Registration Table with IM Logo size 60x90cm | E38: 4 | F38: 1
B39: Electrical Installment for booth | C39: KIM | E39: 1 | F39: 1
B41: SIGNAGE : 2x1m , multiplex finishing sticker | D41: KIM | E41: 2 | F41: 1 | H41: =+E41*F41*G41 -> 0
B43: PHOTOBOOTH @ PartnerGathering | C43: KIM | E43: 1 | F43: 1
B44: Flooring 4,88 x 2,44m & Backdrop 4,88 x 3,6m Full finishing Flexy Print German | E44: 1 | F44: 1 | H44: =E44*F44*G44 -> 0
B45: Electrical Installment for booth | C45: KIM | E45: 1 | F45: 1 | H45: =E45*F45*G45 -> 0
B47: SMURF(Communication) Booth size 4x4m H: 3m& PODCAST | C47: KIM | E47: 1 | F47: 1 | H47: =+E47*F47*G47 -> 0
B48: Dinding Size 3x3 | E48: 1 | F48: 1 | H48: =+E48*F48*G48 -> 0
B49: Level Flooring 10cm - Melaminto 3x3m | C49: KIM | E49: 1 | F49: 1 | H49: =+E49*F49*G49 -> 0
B50: Electrical Installment for booth | C50: KIM | E50: 1 | F50: 1
B51: Podcast Equipment - 8.00 -17.00 | C51: KIM | E51: 1 | F51: 1 | H51: =+E51*F51*G51 -> 0 | J51: KENAPA DI SINI ADA PODCAST EQUPIMNET DAN ADA DI CUST EVENT YG LIVE STREAMING APAKAH DOUBLE - 13/11 - tdk double… tetep di harga 12 juta
B52: LED Table rental | E52: 2 | F52: 1 | H52: =+E52*F52*G52 -> 0
B53: Puff LED | E53: 4 | F53: 1 | H53: =+E53*F53*G53 -> 0
B54: WhiteTable rental | E54: 1 | F54: 1 | H54: =+E54*F54*G54 -> 0
B55: Showcase Consumer Products & Transportation from IM | C55: KIM | E55: 1 | F55: 1 | H55: =+E55*F55*G55 -> 0
B57: CYBER SECURITY Booth size 3x3m H:3m | C57: KIM | E57: 1 | F57: 1 | H57: =+E57*F57*G57 -> 0 | J57: 1. Booth - harga booth cyber disamakan - 15.500 - 13/11
B58: Electrical Installment for booth | C58: KIM | E58: 1 | F58: 1
B59: Dinding Size 3x3 | E59: 1 | F59: 1 | H59: =+E59*F59*G59 -> 0
B60: Table Ambalan | E60: 1 | F60: 1 | H60: =+E60*F60*G60 -> 0
B61: Level Flooring 10cm - Melaminto 3x3m | C61: KIM | E61: 1 | F61: 1 | H61: =+E61*F61*G61 -> 0
B62: TV Monitor 43 inch - 4 unit & Sistem ==> karena ini bukan hanya tv saja tapi pakai system ada prosesor, splitter dll | C62: KIM | E62: 1 | F62: 1 | H62: =+E62*F62*G62 -> 0 | J62: Booth - cyber knpa 4 tv harganya 10 juta? - 13/11 | O62: karena bukan hanya sewa tv saja tapi ada systemnya
B63: LED Bar Table | E63: 1 | F63: 1 | H63: =+E63*F63*G63 -> 0
B64: Bar Stool | E64: 3 | F64: 1 | H64: =+E64*F64*G64 -> 0
B65: Showcase Product & Transportation from IM | E65: 3 | F65: 1
B67: INNOVATION HUB size 6x3m | C67: KIM | E67: 1 | F67: 1 | H67: =E67*F67*G67 -> 0
B68: Level Flooring 10cm - Melaminto 3x6m, Lighted at PC AI area | C68: 1 | E68: 1
B69: Table Display | C69: KIM | E69: 3 | F69: 1
B70: Bar Stool | C70: KIM | E70: =3*2 -> 6 | F70: 1 | H70: =+E70*F70*G70 -> 0
B71: Showcase PC AI - Transportation & Product from IM | C71: KIM | E71: 1 | F71: 1
B72: Showcase SI Product & Transportation from IM | E72: 3 | F72: 1
B73: Electrical Installment for booth | C73: KIM | E73: 1 | F73: 1 | H73: =E73*F73*G73 -> 0
H74: =+E74*F74*G74 -> 0
B75: Diamond Sponsor: HPE & APC (TBC)
B76: Diamond Booth 4x3m - Flexy | C76: KIM | E76: 2 | F76: 1 | H76: =+E76*F76*G76 -> 0
B77: Backdrop : 4 x2,4m (tinggi) | C77: KIM | E77: 2 | F77: 1
B78: Level Flooring 10cm - Carpet | C78: KIM | E78: 2 | F78: 1
B79: Electrical Installment for booth | C79: KIM | E79: 1 | F79: 1 | H79: =E79*F79*G79 -> 0
B80: Table Blue Lighted 1 sisi - size 1,22 x 60x T: 90cm | E80: =2*2 -> 4 | F80: 1
B81: LED Table | E81: =1*2 -> 2 | F81: 1 | H81: =+E81*F81*G81 -> 0
B82: Bar Stool : 3 unit | C82: KIM | E82: =2*3 -> 6 | F82: 1 | H82: =+E82*F82*G82 -> 0 | J82: 1. Booth - Telemarketing diamond - drop - 13/11
B83: Event Access - 8 pax | C83: KIM | E83: =8*2 -> 16 | F83: 1 | H83: =E83*F83*G83 -> 0
B85: Platinum Sponsor:
B86: Diamond Booth 4x3m - Flexy | C86: KIM | E86: 1 | F86: 1 | H86: =+E86*F86*G86 -> 0
B87: Backdrop : 4 x2,4m (tinggi) | C87: KIM | E87: 1 | F87: 1
B88: Level Flooring 10cm - Carpet | C88: KIM | E88: 1 | F88: 1
B89: Electrical Installment for booth | C89: KIM | E89: 1 | F89: 1 | H89: =E89*F89*G89 -> 0
B90: Table Blue Lighted 1 sisi - size 1,22 x 60x T: 90cm | E90: 2 | F90: 1
B91: LED Table | E91: 2 | F91: 1 | H91: =+E91*F91*G91 -> 0
B92: Bar Stool : 3 unit | C92: KIM | E92: 3 | F92: 1 | H92: =+E92*F92*G92 -> 0
B93: Telemarketing - 1 months | C93: KIM | E93: 1 | F93: 1 | H93: =E93*F93*G93 -> 0
B94: Event Access - 8 pax | C94: KIM | E94: 8 | F94: 1 | H94: =E94*F94*G94 -> 0
B96: Gold Sponsor:
B97: Gold Booth 3x3m - Flexy | C97: KIM | E97: 1 | F97: 1 | H97: =+E97*F97*G97 -> 0
B98: Backdrop : 3 x2,44m | C98: KIM | E98: 1 | F98: 1
B99: Level Flooring 10cm - Carpet | C99: KIM | E99: 1 | F99: 1
B100: Electrical Installment for booth | C100: KIM | E100: 1 | F100: 1 | H100: =E100*F100*G100 -> 0
B101: Table Blue Lighted 1 sisi - size 1,22 x 60x T: 90cm | E101: 1 | F101: 1
B102: LED Table | E102: 1 | F102: 1 | H102: =+E102*F102*G102 -> 0
B103: Bar Stool : 2 unit | C103: KIM | E103: 2 | F103: 1 | H103: =+E103*F103*G103 -> 0
B104: Event Access - 5 pax | C104: KIM | E104: 5 | F104: 1 | H104: =E104*F104*G104 -> 0
B106: Silver Sponsor Booth
B107: Silver Booth 2x2m - Flexy | C107: KIM | E107: 7 | F107: 1 | H107: =+E107*F107*G107 -> 0
B108: Backdrop : 2 x2,44m
B109: Table Blue Lighted 1 sisi - size 80x60 xT 90cm | E109: 7 | F109: 1
B110: Level Flooring 10cm - Carpet
B111: Electrical Installment for booth | C111: KIM | E111: 1 | F111: 1 | H111: =E111*F111*G111 -> 0
B112: Bar Stool : 2 unit | C112: KIM | E112: =7*2 -> 14 | F112: 1 | H112: =+E112*F112*G112 -> 0
B113: Event Access - 3 pax | C113: KIM | E113: =3*7 -> 21 | F113: 1 | H113: =E113*F113*G113 -> 0
B115: Xvantage Booth
B116: X-Vantage Booth 2x2m - Finshing Duco | C116: KIM | E116: 1 | F116: 1 | H116: =+E116*F116*G116 -> 0
B117: Backdrop : 2 x2,44m - finishing sticker for X & Blue Laptop Table
B118: Storage 60(W)x40x60 (H)cm - Finishing Duco | E118: 1 | F118: 1 | H118: =+E118*F118*G118 -> 0
B119: Level Flooring 10cm - Carpet
B120: Smart TV Touch Screen 50 inch | D120: KIM | E120: 1 | F120: 1 | H120: =+E120*F120*G120 -> 0
B121: Electrical Installment for booth | C121: KIM | E121: 1 | F121: 1
B122: LED Table | E122: 2 | F122: 1 | H122: =E122*F122*G122 -> 0
B123: Bar Stool : 4 unit | C123: KIM | E123: =6-2 -> 4 | F123: 1 | H123: =+E123*F123*G123 -> 0 | J123: 1. Booth - xv 4 pcs saja - 13/11
...

Sheet Hackathon
H7: KIM
A15: Date | B15: : 07 Oct 2025 | E15: Project | F15: : Ingram Micro Innovation Day 2025
A16: Attn | B16: : Abigail Laurencia | E16: Date | F16: : 03 Dec 2025 (Wed)
A17: Client | B17: : PT Ingram Micro Indonesia | E17: Venue | F17: : Shangri-La Hotel, Jakarta
A18: Address | B18: : Jl. Ir. H. Juanda IV No 3B-C | E18: No. Order | F18: : QTN/KIM/2025/VIII/00015 H
B19: Wisma Nugra Santana Lt. 9 Suite 909
B20: Jakarta Pusat 10250
A23: NO | B23: DESCRIPTION | C23: PIC | D23: QTY | E23: Freq | F23: Price-unit | G23: Sub Total
A25: A | B25: Ingram Micro Innovation Day 2025
B26: Hackathon Event
A28: 1 | B28: Venue
B29: Alt 1 .Full Day Package @ Ashley Tanah Abang - dibagi 3 room | C29: KIM | D29: 50 | E29: 1 | F29: 550000 | G29: =D29*E29*F29 -> 27500000
B30: Alt 2: Full Day Package @ Pullman ; dibagi 3 Room | D30: 50 | E30: 1 | F30: 950000
B31: Alt 3: Full Day Package @ Shangri-La ; dibagi 3 Room | D31: 50 | E31: 1 | F31: 1000000
B32: Classroom table - 1 table 3 chairs | D32: 16 | E32: 1
B33: LCD Projector + Screen
B34: Stage Module
B36: D Day-EVENT : include preparation | C36: KIM | D36: 1 | E36: 1 | F36: 37500000 | G36: =D36*E36*F36 -> 37500000
B37: Team work : Project Officer , SD, VJ, LO MC, Stage Mgr, Crew | D37: 1 | E37: 1 | G37: =D37*E37*F37 -> 0
B38: LO Group | D38: 1 | E38: 1
B39: Facilitator per category | D39: 1 | E39: 1 | G39: =D39*E39*F39 -> 0
B40: MC | D40: 1 | E40: 1
B41: Runner | D41: 1 | E41: 1 | G41: =D41*E41*F41 -> 0
B42: Mentor /category | D42: 3 | E42: 1
B43: Independent Judges/category | C43: KIM | D43: 3 | E43: 1 | F43: 12500000 | G43: =D43*E43*F43 -> 37500000
B44: Microsite Hackathon - One link to IMID website | C44: KIM | D44: 1 | E44: 1 | F44: 1500000 | G44: =D44*E44*F44 -> 1500000
A46: 2 | B46: Documentation on D Day event
B47: Photografer | C47: KIM | D47: 1 | E47: 1 | F47: 1750000 | G47: =D47*E47*F47 -> 1750000
B48: Video For Documentation include highlight editing | C48: KIM | D48: 1 | E48: 1 | F48: 3000000 | G48: =D48*E48*F48 -> 3000000
A50: 3 | B50: Creative
B51: Bumper Still for speaker, Design EDM , IG | C51: KIM | D51: 1 | E51: 1 | F51: 2500000 | G51: =D51*E51*F51 -> 2500000
A53: 4 | B53: Production
B54: Roll up Banner for 3 rooms | C54: KIM | D54: 6 | E54: 1 | F54: 750000 | G54: =+D54*E54*F54 -> 4500000
B55: Backdrop Photobooth | C55: KIM | D55: 1 | E55: 1 | F55: 5000000 | G55: =+D55*E55*F55 -> 5000000
B56: LED size 2x 3,5m based 40cm | C56: KIM | D56: 3 | E56: 1 | F56: 8500000 | G56: =+D56*E56*F56 -> 25500000
B57: Backdrop ki ka LED size 1,2 x 2m | C57: KIM | D57: 6 | E57: 1 | F57: 2250000 | G57: =+D57*E57*F57 -> 13500000
B58: Sound System for Main brief 1,500 watt | C58: KIM | D58: 1 | E58: 1 | F58: 3000000 | G58: =+D58*E58*F58 -> 3000000
B59: Sound System for other 2 BO rooms - standart - from Hotel
B60: Signage Registration & Agenda Size A1 , Tripod | C60: KIM | D60: 1 | E60: 1 | F60: 550000 | G60: =+D60*E60*F60 -> 550000
B61: TV for Agenda info (55') + standee @ Registration area | C61: KIM | D61: 1 | E61: 1 | F61: 1750000 | G61: =+D61*E61*F61 -> 1750000
A63: 5 | B63: Build Momentum from Hackation Event - PR Package
B64: Media Brief: 20 media @ IM Office - Theater Style | C64: KIM | D64: 1 | E64: 1 | F64: 40000000 | G64: =D64*E64*F64 -> 40000000
B65: Snack box plus coffee Tomoro | C65: KIM | D65: 30 | E65: 1 | F65: 75000 | G65: =D65*E65*F65 -> 2250000
A67: 6 | B67: Souvenir
B68: T-shirt include logo | C68: KIM | D68: 75 | E68: 1 | F68: 125000 | G68: =+D68*E68*F68 -> 9375000
A70: 7 | B70: Prizes
B71: Piagam | C71: KIM | D71: 6 | E71: 1 | F71: 100000 | G71: =+D71*E71*F71 -> 600000
B72: CASH: Winner 1 : 25 juta @ 3 kategori , Winner Hiburan : 10 juta x3 pax | C72: KIM | D72: 1 | E72: 1 | F72: 105000000 | G72: =+D72*E72*F72 -> 105000000
B73: Medale - 3 tim @ 5 org | C73: KIM | D73: 15 | E73: 1 | F73: 275000 | G73: =+D73*E73*F73 -> 4125000
A75: 8 | B75: Other Cost
B76: Communication & Reporting | C76: KIM | D76: 1 | E76: 3 | F76: 1750000 | G76: =D76*E76*F76 -> 5250000
B77: Lanyard + Name Badge | C77: KIM | D77: 75 | E77: 1 | F77: 35000 | G77: =D77*E77*F77 -> 2625000
A79: B | B79: Additional
B81: PRE-EVENT : include D day Preparation | C81: KIM | D81: 1 | E81: 3 | F81: 65000000
B82: Project Mgr | C82: KIM | D82: 1 | E82: 3
B83: University & Community RO | C83: KIM | D83: 1 | E83: 3
B84: Assessment Officer | C84: KIM | D84: 1 | E84: 3
B85: Content & Developer Officer | C85: KIM | D85: 1 | E85: 3
B86: Admin & Registration | C86: KIM | D86: 2 | E86: 3
B88: Database Community & Telemarketing Mgt
B89: Hackathon Community | C89: KIM | D89: 2 | E89: 1 | F89: 3500000
G92: =SUM(G24:G91) -> 334275000
B93: Sub Total | G93: =+G92 -> 334275000
B94: Agency Fee | G94: =+G93*10% -> 33427500
B95: Total | G95: =+G93+G94 -> 367702500
B96: PPN 11% | G96: =+G95*11% -> 40447275
B97: Grand Total | G97: =+G95+G96 -> 408149775
A100: Note (Contract, Term & Condition) :
A101: 1 | B101: The Price Included PPn 11 %
A102: 2 | B102: Approval needed latest one month before in related to 3rd party
A103: 3 | B103: Cancellation fee 25 % from total amount of the project if the contract has been signed
A104: 4 | B104: Term of payment :
B105: 100 % payment after project finish
B106: Payment Transfer to : PT Kemenangan Indah Makmur
B107: Bank BCA Branch : Pondok Indah
B108: account IDR : 731.065.558.3
B109: account USD : 731.096.766.6
B110: NPWP : 02.098.562.8-013.000
B112: Prepared by : | F112: Approved by,
B119: Fanny Suwarni | F119: Abigail Laurencia
B120: KIM Marketing Services | F120: PT Ingram Micro Indonesia

Sheet Summary
B6: Description | C6: Total Budget | D6: ASF | E6: Grand Total
B7: KOL Sosmed | C7: ='KOL SocMed '!F39 -> 31000000 | D7: ='KOL SocMed '!F40 -> 0 | E7: =+C7+D7 -> 31000000
B8: PR Package BEM | C8: ='PR Package BEM'!G79 -> 45000000 | D8: =C8*10% -> 4500000 | E8: =+C8+D8 -> 49500000
B9: Registration | C9: =Registration!G33 -> 8000000 | D9: =C9*10% -> 800000 | E9: =+C9+D9 -> 8800000
B10: Customer Event | C10: ='Customer Event'!G107 -> 151076922 | D10: =C10*10% -> 15107692 | E10: =+C10+D10 -> 1.6618461e+08
B11: Partner Event | C11: ='Partner Event'!G67 -> 22500000 | D11: =C11*10% -> 2250000 | E11: =+C11+D11 -> 24750000
B12: Booth | C12: =Booth!H130 -> 0 | D12: =C12*10% -> 0 | E12: =+C12+D12 -> 0
E14: =SUM(E7:E13) -> 2.8023461e+08
